{"type":"Topology","arcs":[[[0,569],[51,75],[58,19],[-20,87],[48,27],[27,-50],[36,-2],[32,61],[35,-25],[0,-51],[98,-10],[39,-22],[117,33],[33,30],[64,-31],[68,-4],[-37,-56],[51,-84],[-52,-34],[6,-67],[107,-11],[4,-42],[-50,-9],[-9,-37],[-46,-20],[-43,-61],[-69,-32],[-27,-69],[-26,-165],[-73,-19],[-127,64],[-108,27],[-44,176],[1,204],[-23,58],[24,31],[-145,9]]],"transform":{"scale":[0.0003345333333333256,0.000294250636132319],"translate":[114.054404,36.34318]},"objects":{"json":{"type":"GeometryCollection","geometries":[{"arcs":[[0]],"type":"Polygon","properties":{"adcode":130406,"level":"district","name":"峰峰矿区","parent":{"adcode":130400},"childrenNum":0,"center":[114.212571,36.419298],"centroid":[114.212571,36.419298]}}]}}}